setup.py
envplus/__init__.py
envplus/cli.py
envplus/env.py
envplus/helpers.py
envplus/pathfile.py
envplus.egg-info/PKG-INFO
envplus.egg-info/SOURCES.txt
envplus.egg-info/dependency_links.txt
envplus.egg-info/entry_points.txt
envplus.egg-info/namespace_packages.txt
envplus.egg-info/not-zip-safe
envplus.egg-info/requires.txt
envplus.egg-info/top_level.txt