Metadata-Version: 1.1
Name: envplus
Version: 0.0.0
Summary: Combine your virtualenvs.
Home-page: http://github.com/jsvine/envplus/
Author: Jeremy Singer-Vine
Author-email: jsvine@gmail.com
License: MIT
Keywords: virtualenv virtualenvwrapper virtual environments
Platform: UNKNOWN
Classifier: Development Status :: 3 - Alpha
Classifier: Intended Audience :: Developers
Classifier: License :: OSI Approved :: MIT License
Classifier: Operating System :: OS Independent
Classifier: Programming Language :: Python :: 2.6
Classifier: Programming Language :: Python :: 2.7
Classifier: Programming Language :: Python :: 3.3
